test/__init__.py
test/test_xyz.py
wxyz/__init__.py
wxyz/cli.py
wxyz-1.0.2.dist-info/LICENSE
wxyz-1.0.2.dist-info/METADATA
wxyz-1.0.2.dist-info/WHEEL
wxyz-1.0.2.dist-info/entry_points.txt
wxyz-1.0.2.dist-info/top_level.txt
wxyz-1.0.2.dist-info/RECORD
